{
  "Name": "WMUH2_flt_spm_god_null_8s_tnail_1_15",
  "GeneralInformation": {
    "ID": 2696,
    "Description": "WMUH2_flt_spm_god_null_8s_tnail_1_15",
    "Building type": "Wood Multi-Unit or Hotel or Motel 2 stories",
    "Roof Shape": "flat",
    "Roof Cover Type": "SPM",
    "Roof Cover Quality": "Good",
    "Roof Deck Attachment": "8D @ 6\"/6\"",
    "Roof-Wall Connection": "Toe-nail",
    "Shutters": true,
    "Terrain": "Light Suburban"
  },
  "EDP": {
    "Type": "Peak Gust Wind Speed",
    "Unit": [
      1,
      "mph"
    ]
  },
  "DSGroups": [
    {
      "MedianEDP": 144.1894831310872,
      "Beta": 0.1582373675152021,
      "CurveType": "LogNormal",
      "DSGroupType": "Single",
      "DamageStates": [
        {
          "Weight": 1.0,
          "Consequences": {
            "ReconstructionCost": {
              "Amount": 0.6130909939284671
            }
          },
          "Description": "Minor"
        }
      ]
    },
    {
      "MedianEDP": 158.6673503474541,
      "Beta": 0.1484623024543692,
      "CurveType": "LogNormal",
      "DSGroupType": "Single",
      "DamageStates": [
        {
          "Weight": 1.0,
          "Consequences": {
            "ReconstructionCost": {
              "Amount": 1.0
            }
          },
          "Description": "Moderate"
        }
      ]
    },
    {
      "MedianEDP": 181.5946054349875,
      "Beta": 0.1258705111576903,
      "CurveType": "LogNormal",
      "DSGroupType": "Single",
      "DamageStates": [
        {
          "Weight": 1.0,
          "Consequences": {
            "ReconstructionCost": {
              "Amount": 1.0
            }
          },
          "Description": "Severe"
        }
      ]
    },
    {
      "MedianEDP": 185.3128842793703,
      "Beta": 0.1238083621950763,
      "CurveType": "LogNormal",
      "DSGroupType": "Single",
      "DamageStates": [
        {
          "Weight": 1.0,
          "Consequences": {
            "ReconstructionCost": {
              "Amount": 1.0
            }
          },
          "Description": "Destruction"
        }
      ]
    }
  ]
}