{
  "Name": "WMUH2_flt_spm_god_null_6s_tnail_1_35",
  "GeneralInformation": {
    "ID": 2687,
    "Description": "WMUH2_flt_spm_god_null_6s_tnail_1_35",
    "Building type": "Wood Multi-Unit or Hotel or Motel 2 stories",
    "Roof Shape": "flat",
    "Roof Cover Type": "SPM",
    "Roof Cover Quality": "Good",
    "Roof Deck Attachment": "6d/8d mix @ 6\"/6\"",
    "Roof-Wall Connection": "Toe-nail",
    "Shutters": true,
    "Terrain": "Suburban"
  },
  "EDP": {
    "Type": "Peak Gust Wind Speed",
    "Unit": [
      1,
      "mph"
    ]
  },
  "DSGroups": [
    {
      "MedianEDP": 155.2193989846947,
      "Beta": 0.1592975716647844,
      "CurveType": "LogNormal",
      "DSGroupType": "Single",
      "DamageStates": [
        {
          "Weight": 1.0,
          "Consequences": {
            "ReconstructionCost": {
              "Amount": 0.7832594707547047
            }
          },
          "Description": "Minor"
        }
      ]
    },
    {
      "MedianEDP": 170.2646479390529,
      "Beta": 0.1461167877386463,
      "CurveType": "LogNormal",
      "DSGroupType": "Single",
      "DamageStates": [
        {
          "Weight": 1.0,
          "Consequences": {
            "ReconstructionCost": {
              "Amount": 1.0
            }
          },
          "Description": "Moderate"
        }
      ]
    },
    {
      "MedianEDP": 193.9771697629625,
      "Beta": 0.1267800998830569,
      "CurveType": "LogNormal",
      "DSGroupType": "Single",
      "DamageStates": [
        {
          "Weight": 1.0,
          "Consequences": {
            "ReconstructionCost": {
              "Amount": 1.0
            }
          },
          "Description": "Severe"
        }
      ]
    },
    {
      "MedianEDP": 197.5487847786877,
      "Beta": 0.1193122134966883,
      "CurveType": "LogNormal",
      "DSGroupType": "Single",
      "DamageStates": [
        {
          "Weight": 1.0,
          "Consequences": {
            "ReconstructionCost": {
              "Amount": 1.0
            }
          },
          "Description": "Destruction"
        }
      ]
    }
  ]
}