{
  "Name": "WMUH1_flt_bur_god_null_8d_strap_1_70",
  "GeneralInformation": {
    "ID": 1973,
    "Description": "WMUH1_flt_bur_god_null_8d_strap_1_70",
    "Building type": "Wood Multi-Unit or Hotel or Motel 1 story",
    "Roof Shape": "flat",
    "Roof Cover Type": "BUR",
    "Roof Cover Quality": "Good",
    "Roof Deck Attachment": "8d @ 6\"/12\"",
    "Roof-Wall Connection": "Strap",
    "Shutters": true,
    "Terrain": "Light Trees"
  },
  "EDP": {
    "Type": "Peak Gust Wind Speed",
    "Unit": [
      1,
      "mph"
    ]
  },
  "DSGroups": [
    {
      "MedianEDP": 146.4183271833716,
      "Beta": 24.64126072319454,
      "CurveType": "Normal",
      "DSGroupType": "Single",
      "DamageStates": [
        {
          "Weight": 1.0,
          "Consequences": {
            "ReconstructionCost": {
              "Amount": 0.05048882188390659
            }
          },
          "Description": "Minor"
        }
      ]
    },
    {
      "MedianEDP": 162.2070234658748,
      "Beta": 0.1522440924947178,
      "CurveType": "LogNormal",
      "DSGroupType": "Single",
      "DamageStates": [
        {
          "Weight": 1.0,
          "Consequences": {
            "ReconstructionCost": {
              "Amount": 0.1521809441698517
            }
          },
          "Description": "Moderate"
        }
      ]
    },
    {
      "MedianEDP": 198.9571936840753,
      "Beta": 0.1505474128079122,
      "CurveType": "LogNormal",
      "DSGroupType": "Single",
      "DamageStates": [
        {
          "Weight": 1.0,
          "Consequences": {
            "ReconstructionCost": {
              "Amount": 0.4135415546166582
            }
          },
          "Description": "Severe"
        }
      ]
    },
    {
      "MedianEDP": 265.8731424744608,
      "Beta": 27.01013072511438,
      "CurveType": "Normal",
      "DSGroupType": "Single",
      "DamageStates": [
        {
          "Weight": 1.0,
          "Consequences": {
            "ReconstructionCost": {
              "Amount": 1.0
            }
          },
          "Description": "Destruction"
        }
      ]
    }
  ]
}