{
  "Name": "WMUH2_flt_spm_por_null_8s_tnail_1_100",
  "GeneralInformation": {
    "ID": 2719,
    "Description": "WMUH2_flt_spm_por_null_8s_tnail_1_100",
    "Building type": "Wood Multi-Unit or Hotel or Motel 2 stories",
    "Roof Shape": "flat",
    "Roof Cover Type": "SPM",
    "Roof Cover Quality": "Poor",
    "Roof Deck Attachment": "8D @ 6\"/6\"",
    "Roof-Wall Connection": "Toe-nail",
    "Shutters": true,
    "Terrain": "Trees"
  },
  "EDP": {
    "Type": "Peak Gust Wind Speed",
    "Unit": [
      1,
      "mph"
    ]
  },
  "DSGroups": [
    {
      "MedianEDP": 170.5006295024293,
      "Beta": 0.1612303962718655,
      "CurveType": "LogNormal",
      "DSGroupType": "Single",
      "DamageStates": [
        {
          "Weight": 1.0,
          "Consequences": {
            "ReconstructionCost": {
              "Amount": 0.9803176767445199
            }
          },
          "Description": "Minor"
        }
      ]
    },
    {
      "MedianEDP": 186.7383713434308,
      "Beta": 0.1580042800029983,
      "CurveType": "LogNormal",
      "DSGroupType": "Single",
      "DamageStates": [
        {
          "Weight": 1.0,
          "Consequences": {
            "ReconstructionCost": {
              "Amount": 1.0
            }
          },
          "Description": "Moderate"
        }
      ]
    },
    {
      "MedianEDP": 215.6840570612317,
      "Beta": 24.9454706209878,
      "CurveType": "Normal",
      "DSGroupType": "Single",
      "DamageStates": [
        {
          "Weight": 1.0,
          "Consequences": {
            "ReconstructionCost": {
              "Amount": 1.0
            }
          },
          "Description": "Severe"
        }
      ]
    },
    {
      "MedianEDP": 219.7046363400304,
      "Beta": 0.1081534497880243,
      "CurveType": "LogNormal",
      "DSGroupType": "Single",
      "DamageStates": [
        {
          "Weight": 1.0,
          "Consequences": {
            "ReconstructionCost": {
              "Amount": 1.0
            }
          },
          "Description": "Destruction"
        }
      ]
    }
  ]
}