{
  "Name": "WMUH2_flt_bur_por_null_6d_tnail_1_3",
  "GeneralInformation": {
    "ID": 2505,
    "Description": "WMUH2_flt_bur_por_null_6d_tnail_1_3",
    "Building type": "Wood Multi-Unit or Hotel or Motel 2 stories",
    "Roof Shape": "flat",
    "Roof Cover Type": "BUR",
    "Roof Cover Quality": "Poor",
    "Roof Deck Attachment": "6d @ 6\"/12\"",
    "Roof-Wall Connection": "Toe-nail",
    "Shutters": true,
    "Terrain": "Open"
  },
  "EDP": {
    "Type": "Peak Gust Wind Speed",
    "Unit": [
      1,
      "mph"
    ]
  },
  "DSGroups": [
    {
      "MedianEDP": 101.0077825427539,
      "Beta": 0.1868563002610293,
      "CurveType": "LogNormal",
      "DSGroupType": "Single",
      "DamageStates": [
        {
          "Weight": 1.0,
          "Consequences": {
            "ReconstructionCost": {
              "Amount": 0.182452391362083
            }
          },
          "Description": "Minor"
        }
      ]
    },
    {
      "MedianEDP": 112.6359331181733,
      "Beta": 0.174848259688496,
      "CurveType": "LogNormal",
      "DSGroupType": "Single",
      "DamageStates": [
        {
          "Weight": 1.0,
          "Consequences": {
            "ReconstructionCost": {
              "Amount": 0.182452391362083
            }
          },
          "Description": "Moderate"
        }
      ]
    },
    {
      "MedianEDP": 139.6604546453173,
      "Beta": 0.1503644128122763,
      "CurveType": "LogNormal",
      "DSGroupType": "Single",
      "DamageStates": [
        {
          "Weight": 1.0,
          "Consequences": {
            "ReconstructionCost": {
              "Amount": 0.9721665984358905
            }
          },
          "Description": "Severe"
        }
      ]
    },
    {
      "MedianEDP": 175.4122597545365,
      "Beta": 0.1052167060067403,
      "CurveType": "LogNormal",
      "DSGroupType": "Single",
      "DamageStates": [
        {
          "Weight": 1.0,
          "Consequences": {
            "ReconstructionCost": {
              "Amount": 1.0
            }
          },
          "Description": "Destruction"
        }
      ]
    }
  ]
}