{
  "Name": "WMUH1_gab_null_null_0_8s_strap_1_70",
  "GeneralInformation": {
    "ID": 2233,
    "Description": "WMUH1_gab_null_null_0_8s_strap_1_70",
    "Building type": "Wood Multi-Unit or Hotel or Motel 1 story",
    "Roof Shape": "gable",
    "Secondary Water Resistance": false,
    "Roof Deck Attachment": "8D @ 6\"/6\"",
    "Roof-Wall Connection": "Strap",
    "Shutters": true,
    "Terrain": "Light Trees"
  },
  "EDP": {
    "Type": "Peak Gust Wind Speed",
    "Unit": [
      1,
      "mph"
    ]
  },
  "DSGroups": [
    {
      "MedianEDP": 138.4504493533784,
      "Beta": 18.45090388731765,
      "CurveType": "Normal",
      "DSGroupType": "Single",
      "DamageStates": [
        {
          "Weight": 1.0,
          "Consequences": {
            "ReconstructionCost": {
              "Amount": 0.01977206234531679
            }
          },
          "Description": "Minor"
        }
      ]
    },
    {
      "MedianEDP": 170.9895086784522,
      "Beta": 20.76014198068437,
      "CurveType": "Normal",
      "DSGroupType": "Single",
      "DamageStates": [
        {
          "Weight": 1.0,
          "Consequences": {
            "ReconstructionCost": {
              "Amount": 0.182097320310311
            }
          },
          "Description": "Moderate"
        }
      ]
    },
    {
      "MedianEDP": 203.3235615662973,
      "Beta": 0.1298652043599871,
      "CurveType": "LogNormal",
      "DSGroupType": "Single",
      "DamageStates": [
        {
          "Weight": 1.0,
          "Consequences": {
            "ReconstructionCost": {
              "Amount": 0.3815489004451564
            }
          },
          "Description": "Severe"
        }
      ]
    },
    {
      "MedianEDP": 233.1361678120165,
      "Beta": 0.09301643437758322,
      "CurveType": "LogNormal",
      "DSGroupType": "Single",
      "DamageStates": [
        {
          "Weight": 1.0,
          "Consequences": {
            "ReconstructionCost": {
              "Amount": 1.0
            }
          },
          "Description": "Destruction"
        }
      ]
    }
  ]
}