{
  "Name": "WSF1_gab_1_8s_strap_no_0_35",
  "GeneralInformation": {
    "ID": 352,
    "Description": "WSF1_gab_1_8s_strap_no_0_35",
    "Building type": "Wood Single-Family Homes 1 story",
    "Roof Shape": "gable",
    "Secondary Water Resistance": true,
    "Roof Deck Attachment": "8D @ 6\"/6\"",
    "Roof-Wall Connection": "Strap",
    "Garage": "None",
    "Shutters": false,
    "Terrain": "Suburban"
  },
  "EDP": {
    "Type": "Peak Gust Wind Speed",
    "Unit": [
      1,
      "mph"
    ]
  },
  "DSGroups": [
    {
      "MedianEDP": 125.0116064106834,
      "Beta": 16.02825712083792,
      "CurveType": "Normal",
      "DSGroupType": "Single",
      "DamageStates": [
        {
          "Weight": 1.0,
          "Consequences": {
            "ReconstructionCost": {
              "Amount": 0.0775920834070139
            }
          },
          "Description": "Minor"
        }
      ]
    },
    {
      "MedianEDP": 142.6607024558454,
      "Beta": 0.1148444616256423,
      "CurveType": "LogNormal",
      "DSGroupType": "Single",
      "DamageStates": [
        {
          "Weight": 1.0,
          "Consequences": {
            "ReconstructionCost": {
              "Amount": 0.0775920834070139
            }
          },
          "Description": "Moderate"
        }
      ]
    },
    {
      "MedianEDP": 161.3160150342391,
      "Beta": 0.1038125750204435,
      "CurveType": "LogNormal",
      "DSGroupType": "Single",
      "DamageStates": [
        {
          "Weight": 1.0,
          "Consequences": {
            "ReconstructionCost": {
              "Amount": 0.6297968874225762
            }
          },
          "Description": "Severe"
        }
      ]
    },
    {
      "MedianEDP": 180.8390470902914,
      "Beta": 0.1127087203685276,
      "CurveType": "LogNormal",
      "DSGroupType": "Single",
      "DamageStates": [
        {
          "Weight": 1.0,
          "Consequences": {
            "ReconstructionCost": {
              "Amount": 1.0
            }
          },
          "Description": "Destruction"
        }
      ]
    }
  ]
}