{
  "Name": "WSF1_gab_0_6d_tnail_sup_1_35",
  "GeneralInformation": {
    "ID": 42,
    "Description": "WSF1_gab_0_6d_tnail_sup_1_35",
    "Building type": "Wood Single-Family Homes 1 story",
    "Roof Shape": "gable",
    "Secondary Water Resistance": false,
    "Roof Deck Attachment": "6d @ 6\"/12\"",
    "Roof-Wall Connection": "Toe-nail",
    "Garage": "SFBC 1994",
    "Shutters": true,
    "Terrain": "Suburban"
  },
  "EDP": {
    "Type": "Peak Gust Wind Speed",
    "Unit": [
      1,
      "mph"
    ]
  },
  "DSGroups": [
    {
      "MedianEDP": 114.9600052976761,
      "Beta": 16.42154870030675,
      "CurveType": "Normal",
      "DSGroupType": "Single",
      "DamageStates": [
        {
          "Weight": 1.0,
          "Consequences": {
            "ReconstructionCost": {
              "Amount": 0.04377679997841365
            }
          },
          "Description": "Minor"
        }
      ]
    },
    {
      "MedianEDP": 136.7241857925423,
      "Beta": 17.72092666665353,
      "CurveType": "Normal",
      "DSGroupType": "Single",
      "DamageStates": [
        {
          "Weight": 1.0,
          "Consequences": {
            "ReconstructionCost": {
              "Amount": 0.09795464557851694
            }
          },
          "Description": "Moderate"
        }
      ]
    },
    {
      "MedianEDP": 155.5518213455928,
      "Beta": 0.1097991043310065,
      "CurveType": "LogNormal",
      "DSGroupType": "Single",
      "DamageStates": [
        {
          "Weight": 1.0,
          "Consequences": {
            "ReconstructionCost": {
              "Amount": 0.69350567011516
            }
          },
          "Description": "Severe"
        }
      ]
    },
    {
      "MedianEDP": 170.8102628055418,
      "Beta": 0.1205475447082366,
      "CurveType": "LogNormal",
      "DSGroupType": "Single",
      "DamageStates": [
        {
          "Weight": 1.0,
          "Consequences": {
            "ReconstructionCost": {
              "Amount": 1.0
            }
          },
          "Description": "Destruction"
        }
      ]
    }
  ]
}