{
  "Name": "WSF1_hip_0_8d_tnail_no_1_35",
  "GeneralInformation": {
    "ID": 532,
    "Description": "WSF1_hip_0_8d_tnail_no_1_35",
    "Building type": "Wood Single-Family Homes 1 story",
    "Roof Shape": "hip",
    "Secondary Water Resistance": false,
    "Roof Deck Attachment": "8d @ 6\"/12\"",
    "Roof-Wall Connection": "Toe-nail",
    "Garage": "None",
    "Shutters": true,
    "Terrain": "Suburban"
  },
  "EDP": {
    "Type": "Peak Gust Wind Speed",
    "Unit": [
      1,
      "mph"
    ]
  },
  "DSGroups": [
    {
      "MedianEDP": 119.6485460345837,
      "Beta": 16.9868483559362,
      "CurveType": "Normal",
      "DSGroupType": "Single",
      "DamageStates": [
        {
          "Weight": 1.0,
          "Consequences": {
            "ReconstructionCost": {
              "Amount": 0.05325125701286198
            }
          },
          "Description": "Minor"
        }
      ]
    },
    {
      "MedianEDP": 147.5389379969094,
      "Beta": 18.69928007489467,
      "CurveType": "Normal",
      "DSGroupType": "Single",
      "DamageStates": [
        {
          "Weight": 1.0,
          "Consequences": {
            "ReconstructionCost": {
              "Amount": 0.1803226934095495
            }
          },
          "Description": "Moderate"
        }
      ]
    },
    {
      "MedianEDP": 166.4155256163347,
      "Beta": 0.1189487549523028,
      "CurveType": "LogNormal",
      "DSGroupType": "Single",
      "DamageStates": [
        {
          "Weight": 1.0,
          "Consequences": {
            "ReconstructionCost": {
              "Amount": 0.8585182158947566
            }
          },
          "Description": "Severe"
        }
      ]
    },
    {
      "MedianEDP": 182.2688345909647,
      "Beta": 0.1311596697825764,
      "CurveType": "LogNormal",
      "DSGroupType": "Single",
      "DamageStates": [
        {
          "Weight": 1.0,
          "Consequences": {
            "ReconstructionCost": {
              "Amount": 1.0
            }
          },
          "Description": "Destruction"
        }
      ]
    }
  ]
}