{
  "Name": "WSF1_gab_1_8d_strap_no_1_15",
  "GeneralInformation": {
    "ID": 306,
    "Description": "WSF1_gab_1_8d_strap_no_1_15",
    "Building type": "Wood Single-Family Homes 1 story",
    "Roof Shape": "gable",
    "Secondary Water Resistance": true,
    "Roof Deck Attachment": "8d @ 6\"/12\"",
    "Roof-Wall Connection": "Strap",
    "Garage": "None",
    "Shutters": true,
    "Terrain": "Light Suburban"
  },
  "EDP": {
    "Type": "Peak Gust Wind Speed",
    "Unit": [
      1,
      "mph"
    ]
  },
  "DSGroups": [
    {
      "MedianEDP": 108.0997045795512,
      "Beta": 15.54431000595993,
      "CurveType": "Normal",
      "DSGroupType": "Single",
      "DamageStates": [
        {
          "Weight": 1.0,
          "Consequences": {
            "ReconstructionCost": {
              "Amount": 0.02118257673563263
            }
          },
          "Description": "Minor"
        }
      ]
    },
    {
      "MedianEDP": 134.9004257601842,
      "Beta": 17.71354821668763,
      "CurveType": "Normal",
      "DSGroupType": "Single",
      "DamageStates": [
        {
          "Weight": 1.0,
          "Consequences": {
            "ReconstructionCost": {
              "Amount": 0.02118257673563265
            }
          },
          "Description": "Moderate"
        }
      ]
    },
    {
      "MedianEDP": 160.1290760019077,
      "Beta": 19.07460118071119,
      "CurveType": "Normal",
      "DSGroupType": "Single",
      "DamageStates": [
        {
          "Weight": 1.0,
          "Consequences": {
            "ReconstructionCost": {
              "Amount": 0.4610491333543517
            }
          },
          "Description": "Severe"
        }
      ]
    },
    {
      "MedianEDP": 191.6585041587783,
      "Beta": 0.1252550064775233,
      "CurveType": "LogNormal",
      "DSGroupType": "Single",
      "DamageStates": [
        {
          "Weight": 1.0,
          "Consequences": {
            "ReconstructionCost": {
              "Amount": 1.0
            }
          },
          "Description": "Destruction"
        }
      ]
    }
  ]
}