{
  "Name": "WSF1_gab_0_6s_strap_sup_1_100",
  "GeneralInformation": {
    "ID": 69,
    "Description": "WSF1_gab_0_6s_strap_sup_1_100",
    "Building type": "Wood Single-Family Homes 1 story",
    "Roof Shape": "gable",
    "Secondary Water Resistance": false,
    "Roof Deck Attachment": "6d/8d mix @ 6\"/6\"",
    "Roof-Wall Connection": "Strap",
    "Garage": "SFBC 1994",
    "Shutters": true,
    "Terrain": "Trees"
  },
  "EDP": {
    "Type": "Peak Gust Wind Speed",
    "Unit": [
      1,
      "mph"
    ]
  },
  "DSGroups": [
    {
      "MedianEDP": 143.1126007850882,
      "Beta": 19.03752291510565,
      "CurveType": "Normal",
      "DSGroupType": "Single",
      "DamageStates": [
        {
          "Weight": 1.0,
          "Consequences": {
            "ReconstructionCost": {
              "Amount": 0.0141052385962385
            }
          },
          "Description": "Minor"
        }
      ]
    },
    {
      "MedianEDP": 175.7383600740402,
      "Beta": 20.58146643418026,
      "CurveType": "Normal",
      "DSGroupType": "Single",
      "DamageStates": [
        {
          "Weight": 1.0,
          "Consequences": {
            "ReconstructionCost": {
              "Amount": 0.2374018711425404
            }
          },
          "Description": "Moderate"
        }
      ]
    },
    {
      "MedianEDP": 206.5699437772833,
      "Beta": 23.70553842916075,
      "CurveType": "Normal",
      "DSGroupType": "Single",
      "DamageStates": [
        {
          "Weight": 1.0,
          "Consequences": {
            "ReconstructionCost": {
              "Amount": 0.7449554325375591
            }
          },
          "Description": "Severe"
        }
      ]
    },
    {
      "MedianEDP": 237.6073794013496,
      "Beta": 21.07624922280631,
      "CurveType": "Normal",
      "DSGroupType": "Single",
      "DamageStates": [
        {
          "Weight": 1.0,
          "Consequences": {
            "ReconstructionCost": {
              "Amount": 1.0
            }
          },
          "Description": "Destruction"
        }
      ]
    }
  ]
}