{
  "Name": "WSF2_hip_1_6s_strap_sup_1_3",
  "GeneralInformation": {
    "ID": 1465,
    "Description": "WSF2_hip_1_6s_strap_sup_1_3",
    "Building type": "Wood Single-Family Homes 2+ stories",
    "Roof Shape": "hip",
    "Secondary Water Resistance": true,
    "Roof Deck Attachment": "6d/8d mix @ 6\"/6\"",
    "Roof-Wall Connection": "Strap",
    "Garage": "SFBC 1994",
    "Shutters": true,
    "Terrain": "Open"
  },
  "EDP": {
    "Type": "Peak Gust Wind Speed",
    "Unit": [
      1,
      "mph"
    ]
  },
  "DSGroups": [
    {
      "MedianEDP": 111.3939631815607,
      "Beta": 15.72115754235135,
      "CurveType": "Normal",
      "DSGroupType": "Single",
      "DamageStates": [
        {
          "Weight": 1.0,
          "Consequences": {
            "ReconstructionCost": {
              "Amount": 0.05899415839637021
            }
          },
          "Description": "Minor"
        }
      ]
    },
    {
      "MedianEDP": 136.9094772830148,
      "Beta": 18.04329869561119,
      "CurveType": "Normal",
      "DSGroupType": "Single",
      "DamageStates": [
        {
          "Weight": 1.0,
          "Consequences": {
            "ReconstructionCost": {
              "Amount": 0.05899415839637022
            }
          },
          "Description": "Moderate"
        }
      ]
    },
    {
      "MedianEDP": 155.6175118294208,
      "Beta": 17.4189590955482,
      "CurveType": "Normal",
      "DSGroupType": "Single",
      "DamageStates": [
        {
          "Weight": 1.0,
          "Consequences": {
            "ReconstructionCost": {
              "Amount": 0.1693927942361086
            }
          },
          "Description": "Severe"
        }
      ]
    },
    {
      "MedianEDP": 169.9973257500112,
      "Beta": 0.09554873085549852,
      "CurveType": "LogNormal",
      "DSGroupType": "Single",
      "DamageStates": [
        {
          "Weight": 1.0,
          "Consequences": {
            "ReconstructionCost": {
              "Amount": 1.0
            }
          },
          "Description": "Destruction"
        }
      ]
    }
  ]
}