{
  "Name": "WSF2_hip_0_8d_tnail_std_0_100",
  "GeneralInformation": {
    "ID": 1339,
    "Description": "WSF2_hip_0_8d_tnail_std_0_100",
    "Building type": "Wood Single-Family Homes 2+ stories",
    "Roof Shape": "hip",
    "Secondary Water Resistance": false,
    "Roof Deck Attachment": "8d @ 6\"/12\"",
    "Roof-Wall Connection": "Toe-nail",
    "Garage": "Standard",
    "Shutters": false,
    "Terrain": "Trees"
  },
  "EDP": {
    "Type": "Peak Gust Wind Speed",
    "Unit": [
      1,
      "mph"
    ]
  },
  "DSGroups": [
    {
      "MedianEDP": 113.9491742144594,
      "Beta": 15.63372994166469,
      "CurveType": "Normal",
      "DSGroupType": "Single",
      "DamageStates": [
        {
          "Weight": 1.0,
          "Consequences": {
            "ReconstructionCost": {
              "Amount": 0.03493344359897729
            }
          },
          "Description": "Minor"
        }
      ]
    },
    {
      "MedianEDP": 137.8188563883153,
      "Beta": 16.28706767252082,
      "CurveType": "Normal",
      "DSGroupType": "Single",
      "DamageStates": [
        {
          "Weight": 1.0,
          "Consequences": {
            "ReconstructionCost": {
              "Amount": 0.1594388407780982
            }
          },
          "Description": "Moderate"
        }
      ]
    },
    {
      "MedianEDP": 152.7897691191245,
      "Beta": 15.11189906946196,
      "CurveType": "Normal",
      "DSGroupType": "Single",
      "DamageStates": [
        {
          "Weight": 1.0,
          "Consequences": {
            "ReconstructionCost": {
              "Amount": 0.7012639755174764
            }
          },
          "Description": "Severe"
        }
      ]
    },
    {
      "MedianEDP": 164.9402399441766,
      "Beta": 0.09939399869507771,
      "CurveType": "LogNormal",
      "DSGroupType": "Single",
      "DamageStates": [
        {
          "Weight": 1.0,
          "Consequences": {
            "ReconstructionCost": {
              "Amount": 1.0
            }
          },
          "Description": "Destruction"
        }
      ]
    }
  ]
}