{
  "Name": "WSF2_gab_0_8d_strap_no_1_15",
  "GeneralInformation": {
    "ID": 906,
    "Description": "WSF2_gab_0_8d_strap_no_1_15",
    "Building type": "Wood Single-Family Homes 2+ stories",
    "Roof Shape": "gable",
    "Secondary Water Resistance": false,
    "Roof Deck Attachment": "8d @ 6\"/12\"",
    "Roof-Wall Connection": "Strap",
    "Garage": "None",
    "Shutters": true,
    "Terrain": "Light Suburban"
  },
  "EDP": {
    "Type": "Peak Gust Wind Speed",
    "Unit": [
      1,
      "mph"
    ]
  },
  "DSGroups": [
    {
      "MedianEDP": 98.28149370724172,
      "Beta": 14.22012809737535,
      "CurveType": "Normal",
      "DSGroupType": "Single",
      "DamageStates": [
        {
          "Weight": 1.0,
          "Consequences": {
            "ReconstructionCost": {
              "Amount": 0.0204875284861538
            }
          },
          "Description": "Minor"
        }
      ]
    },
    {
      "MedianEDP": 122.4385439187517,
      "Beta": 16.5373201508485,
      "CurveType": "Normal",
      "DSGroupType": "Single",
      "DamageStates": [
        {
          "Weight": 1.0,
          "Consequences": {
            "ReconstructionCost": {
              "Amount": 0.1746324184019072
            }
          },
          "Description": "Moderate"
        }
      ]
    },
    {
      "MedianEDP": 145.2588364650665,
      "Beta": 17.59268340846094,
      "CurveType": "Normal",
      "DSGroupType": "Single",
      "DamageStates": [
        {
          "Weight": 1.0,
          "Consequences": {
            "ReconstructionCost": {
              "Amount": 0.8486655094836485
            }
          },
          "Description": "Severe"
        }
      ]
    },
    {
      "MedianEDP": 166.4880714479291,
      "Beta": 0.116521117628685,
      "CurveType": "LogNormal",
      "DSGroupType": "Single",
      "DamageStates": [
        {
          "Weight": 1.0,
          "Consequences": {
            "ReconstructionCost": {
              "Amount": 1.0
            }
          },
          "Description": "Destruction"
        }
      ]
    }
  ]
}