{
  "Name": "WSF2_hip_1_6s_strap_sup_1_70",
  "GeneralInformation": {
    "ID": 1468,
    "Description": "WSF2_hip_1_6s_strap_sup_1_70",
    "Building type": "Wood Single-Family Homes 2+ stories",
    "Roof Shape": "hip",
    "Secondary Water Resistance": true,
    "Roof Deck Attachment": "6d/8d mix @ 6\"/6\"",
    "Roof-Wall Connection": "Strap",
    "Garage": "SFBC 1994",
    "Shutters": true,
    "Terrain": "Light Trees"
  },
  "EDP": {
    "Type": "Peak Gust Wind Speed",
    "Unit": [
      1,
      "mph"
    ]
  },
  "DSGroups": [
    {
      "MedianEDP": 129.339008112555,
      "Beta": 17.4869980554827,
      "CurveType": "Normal",
      "DSGroupType": "Single",
      "DamageStates": [
        {
          "Weight": 1.0,
          "Consequences": {
            "ReconstructionCost": {
              "Amount": 0.02305201107146128
            }
          },
          "Description": "Minor"
        }
      ]
    },
    {
      "MedianEDP": 157.730581556118,
      "Beta": 19.80118830464727,
      "CurveType": "Normal",
      "DSGroupType": "Single",
      "DamageStates": [
        {
          "Weight": 1.0,
          "Consequences": {
            "ReconstructionCost": {
              "Amount": 0.03736108578346454
            }
          },
          "Description": "Moderate"
        }
      ]
    },
    {
      "MedianEDP": 180.9465297241298,
      "Beta": 20.11668538962522,
      "CurveType": "Normal",
      "DSGroupType": "Single",
      "DamageStates": [
        {
          "Weight": 1.0,
          "Consequences": {
            "ReconstructionCost": {
              "Amount": 0.4355402489807599
            }
          },
          "Description": "Severe"
        }
      ]
    },
    {
      "MedianEDP": 215.632635999258,
      "Beta": 0.1228877242132299,
      "CurveType": "LogNormal",
      "DSGroupType": "Single",
      "DamageStates": [
        {
          "Weight": 1.0,
          "Consequences": {
            "ReconstructionCost": {
              "Amount": 1.0
            }
          },
          "Description": "Destruction"
        }
      ]
    }
  ]
}