{
  "Name": "WSF2_hip_0_8d_strap_std_0_35",
  "GeneralInformation": {
    "ID": 1312,
    "Description": "WSF2_hip_0_8d_strap_std_0_35",
    "Building type": "Wood Single-Family Homes 2+ stories",
    "Roof Shape": "hip",
    "Secondary Water Resistance": false,
    "Roof Deck Attachment": "8d @ 6\"/12\"",
    "Roof-Wall Connection": "Strap",
    "Garage": "Standard",
    "Shutters": false,
    "Terrain": "Suburban"
  },
  "EDP": {
    "Type": "Peak Gust Wind Speed",
    "Unit": [
      1,
      "mph"
    ]
  },
  "DSGroups": [
    {
      "MedianEDP": 106.0990199088156,
      "Beta": 14.28663038463728,
      "CurveType": "Normal",
      "DSGroupType": "Single",
      "DamageStates": [
        {
          "Weight": 1.0,
          "Consequences": {
            "ReconstructionCost": {
              "Amount": 0.06616827866822596
            }
          },
          "Description": "Minor"
        }
      ]
    },
    {
      "MedianEDP": 126.3765844315228,
      "Beta": 14.46020778172402,
      "CurveType": "Normal",
      "DSGroupType": "Single",
      "DamageStates": [
        {
          "Weight": 1.0,
          "Consequences": {
            "ReconstructionCost": {
              "Amount": 0.06786867161831751
            }
          },
          "Description": "Moderate"
        }
      ]
    },
    {
      "MedianEDP": 139.9949424795514,
      "Beta": 13.44591306206904,
      "CurveType": "Normal",
      "DSGroupType": "Single",
      "DamageStates": [
        {
          "Weight": 1.0,
          "Consequences": {
            "ReconstructionCost": {
              "Amount": 0.7869676106131956
            }
          },
          "Description": "Severe"
        }
      ]
    },
    {
      "MedianEDP": 166.2280878325603,
      "Beta": 0.09893470612872358,
      "CurveType": "LogNormal",
      "DSGroupType": "Single",
      "DamageStates": [
        {
          "Weight": 1.0,
          "Consequences": {
            "ReconstructionCost": {
              "Amount": 1.0
            }
          },
          "Description": "Destruction"
        }
      ]
    }
  ]
}