{
  "Name": "Prefabricated steel stair with steel treads and landings with no seismic joint.",
  "QuantityUnit": [
    1,
    "EA"
  ],
  "Directional": true,
  "Correlated": false,
  "EDP": {
    "Type": "Story Drift Ratio",
    "Unit": [
      1,
      "ea"
    ],
    "Offset": 0
  },
  "GeneralInformation": {
    "ID": "C2011.001b",
    "Description": "Flexible stair without seismic interstory slip joint.  Steel prefab stringers, steel or concrete filled pan treads.",
    "Author": "Not Given",
    "Official": true,
    "DateCreated": "2019-02-19T17:50:15.0582146-08:00",
    "Approved": true,
    "Incomplete": false,
    "Notes": "Confirm median demand and dispersion values"
  },
  "Ratings": {
    "DataQuality": "Marginal",
    "DataRelevance": "Marginal",
    "Documentation": "Average",
    "Rationality": "Not Rated"
  },
  "DSGroups": [
    {
      "MedianEDP": 0.005,
      "Beta": 0.6,
      "CurveType": "LogNormal",
      "DSGroupType": "Single",
      "DamageStates": [
        {
          "Weight": 1.0,
          "LongLeadTime": false,
          "Consequences": {
            "RedTag": {
              "Amount": 0.0,
              "Beta": 0.0,
              "CurveType": "Normal",
              "Bounds": [
                0.0,
                1.0
              ]
            },
            "ReconstructionCost": {
              "Amount": [
                4340.0,
                1302.0
              ],
              "Quantity": [
                1.0,
                10.0
              ],
              "CurveType": "Normal",
              "Beta": 0.4586,
              "Bounds": [
                0,
                "None"
              ]
            },
            "ReconstructionTime": {
              "Amount": [
                3.3813,
                1.0135
              ],
              "Quantity": [
                1.0,
                10.0
              ],
              "CurveType": "Normal",
              "Beta": 0.5223,
              "Bounds": [
                0,
                "None"
              ]
            }
          },
          "Description": "Non structural damage, local steel yielding.",
          "RepairMeasures": "Patch, paint.",
          "DamageImageName": "C2011.001a-DS1-1.jpg"
        }
      ]
    },
    {
      "MedianEDP": 0.017,
      "Beta": 0.6,
      "CurveType": "LogNormal",
      "DSGroupType": "Single",
      "DamageStates": [
        {
          "Weight": 1.0,
          "LongLeadTime": false,
          "Consequences": {
            "RedTag": {
              "Amount": 0.0,
              "Beta": 0.0,
              "CurveType": "Normal",
              "Bounds": [
                0.0,
                1.0
              ]
            },
            "ReconstructionCost": {
              "Amount": [
                11100.0,
                3330.0
              ],
              "Quantity": [
                1.0,
                10.0
              ],
              "CurveType": "Normal",
              "Beta": 0.4859,
              "Bounds": [
                0,
                "None"
              ]
            },
            "ReconstructionTime": {
              "Amount": [
                8.6157,
                2.5597
              ],
              "Quantity": [
                1.0,
                10.0
              ],
              "CurveType": "Normal",
              "Beta": 0.5465,
              "Bounds": [
                0,
                "None"
              ]
            }
          },
          "Description": "Buckling of steel, weld cracking.",
          "RepairMeasures": "Removal and replacement of damaged components.  Field repair of damage (such as welding).  Repair finsihes.",
          "DamageImageName": "C2011.001a-DS2-1.jpg"
        }
      ]
    },
    {
      "MedianEDP": 0.028,
      "Beta": 0.45,
      "CurveType": "LogNormal",
      "DSGroupType": "Single",
      "DamageStates": [
        {
          "Weight": 1.0,
          "LongLeadTime": false,
          "Consequences": {
            "RedTag": {
              "Amount": 0.75,
              "Beta": 0.5,
              "CurveType": "Normal",
              "Bounds": [
                0.0,
                1.0
              ]
            },
            "ReconstructionCost": {
              "Amount": [
                37600.0,
                11280.0
              ],
              "Quantity": [
                1.0,
                10.0
              ],
              "CurveType": "LogNormal",
              "Beta": 0.0969,
              "Bounds": [
                0,
                "None"
              ]
            },
            "ReconstructionTime": {
              "Amount": [
                29.3429,
                8.8288
              ],
              "Quantity": [
                1.0,
                10.0
              ],
              "CurveType": "LogNormal",
              "Beta": 0.2681,
              "Bounds": [
                0,
                "None"
              ]
            }
          },
          "Description": "Loss of live load capacity.  Connection and or weld fracture.",
          "RepairMeasures": "Replace stair and handrail.  Repair and replace affected soffits and floor finishes.",
          "DamageImageName": "C2011.001a-DS2-1.jpg"
        }
      ]
    }
  ]
}