{
  "Name": "Chiller - Capacity: < 100 Ton - Unanchored equipment that is not vibration isolated - Equipment fragility only",
  "QuantityUnit": [
    1,
    "ea"
  ],
  "Directional": false,
  "Correlated": false,
  "EDP": {
    "Type": "Peak Floor Acceleration",
    "Unit": [
      1,
      "g"
    ],
    "Offset": 0
  },
  "GeneralInformation": {
    "ID": "D3031.011a",
    "Description": "Costing is per unit and is based upon 75 Ton.",
    "Author": "Not Given",
    "Official": true,
    "DateCreated": "2019-02-19T17:50:38.4381985-08:00",
    "Approved": true,
    "Incomplete": false,
    "Notes": "None"
  },
  "Ratings": {
    "DataQuality": "Average",
    "DataRelevance": "Average",
    "Documentation": "Superior",
    "Rationality": "Superior"
  },
  "DSGroups": [
    {
      "MedianEDP": 0.2,
      "Beta": 0.4,
      "CurveType": "LogNormal",
      "DSGroupType": "Single",
      "DamageStates": [
        {
          "Weight": 1.0,
          "LongLeadTime": false,
          "Consequences": {
            "ReconstructionCost": {
              "Amount": [
                50820.0,
                41580.0
              ],
              "Quantity": [
                1.0,
                5.0
              ],
              "CurveType": "LogNormal",
              "Beta": 0.1785,
              "Bounds": [
                0,
                "None"
              ]
            },
            "ReconstructionTime": {
              "Amount": [
                14.2677,
                4.7559
              ],
              "Quantity": [
                1.0,
                5.0
              ],
              "CurveType": "LogNormal",
              "Beta": 0.3072,
              "Bounds": [
                0,
                "None"
              ]
            }
          },
          "Description": "Damaged, inoperative.",
          "RepairMeasures": "Repair chiller and attached piping.  Chiller removed, repaired offsite, and reinstalled."
        }
      ]
    }
  ]
}